moonai/__init__.py
moonai/agent.py
moonai/llm.py
moonai/mission.py
moonai/process.py
moonai/squad.py
moonai/agents/__init__.py
moonai/agents/parser.py
moonai/agents/squad_agent_executor.py
moonai/agents/tools_handler.py
moonai/agents/agent_builder/__init__.py
moonai/agents/agent_builder/base_agent.py
moonai/agents/agent_builder/base_agent_executor_mixin.py
moonai/agents/agent_builder/utilities/__init__.py
moonai/agents/agent_builder/utilities/base_output_converter.py
moonai/agents/agent_builder/utilities/base_token_process.py
moonai/agents/cache/__init__.py
moonai/agents/cache/cache_handler.py
moonai/cli/__init__.py
moonai/cli/add_squad_to_flow.py
moonai/cli/cli.py
moonai/cli/command.py
moonai/cli/config.py
moonai/cli/constants.py
moonai/cli/create_flow.py
moonai/cli/create_pipeline.py
moonai/cli/create_squad.py
moonai/cli/evaluate_squad.py
moonai/cli/git.py
moonai/cli/install_squad.py
moonai/cli/kickoff_flow.py
moonai/cli/plot_flow.py
moonai/cli/plus_api.py
moonai/cli/provider.py
moonai/cli/replay_from_mission.py
moonai/cli/reset_memories_command.py
moonai/cli/run_squad.py
moonai/cli/train_squad.py
moonai/cli/update_squad.py
moonai/cli/utils.py
moonai/cli/authentication/__init__.py
moonai/cli/authentication/constants.py
moonai/cli/authentication/main.py
moonai/cli/authentication/utils.py
moonai/cli/deploy/__init__.py
moonai/cli/deploy/main.py
moonai/cli/templates/__init__.py
moonai/cli/templates/flow/.gitignore
moonai/cli/templates/flow/README.md
moonai/cli/templates/flow/__init__.py
moonai/cli/templates/flow/main.py
moonai/cli/templates/flow/pyproject.toml
moonai/cli/templates/flow/squads/poem_squad/poem_squad.py
moonai/cli/templates/flow/squads/poem_squad/config/agents.yaml
moonai/cli/templates/flow/squads/poem_squad/config/missions.yaml
moonai/cli/templates/flow/tools/__init__.py
moonai/cli/templates/flow/tools/custom_tool.py
moonai/cli/templates/pipeline/.gitignore
moonai/cli/templates/pipeline/README.md
moonai/cli/templates/pipeline/__init__.py
moonai-0.3.0.dist-info/METADATA
moonai-0.3.0.dist-info/WHEEL
moonai-0.3.0.dist-info/entry_points.txt
moonai-0.3.0.dist-info/licenses/LICENSE
moonai-0.3.0.dist-info/RECORD
