Metadata-Version: 2.3
Name: moonai
Version: 0.3.0
Summary: Cutting-edge framework for orchestrating role-playing, autonomous AI agents. By fostering collaborative intelligence, moonai empowers agents to work together seamlessly, tackling complex missions.
Project-URL: Homepage, https://moonai.dev
Project-URL: Documentation, https://docs.moonai.dev
Project-URL: Repository, https://github.com/brunobracaioli/moonai
Author-email: Bruno Bracaioli <bruno@bracaiolitech.com>
Requires-Python: <=3.13,>=3.10
Requires-Dist: appdirs>=1.4.4
Requires-Dist: auth0-python>=4.7.1
Requires-Dist: beautifulsoup4>=4.12.3
Requires-Dist: chromadb>=0.5.18
Requires-Dist: click>=8.1.7
Requires-Dist: docker>=7.1.0
Requires-Dist: docx2txt>=0.8
Requires-Dist: embedchain>=0.1.114
Requires-Dist: instructor>=1.3.3
Requires-Dist: json-repair>=0.25.2
Requires-Dist: jsonref>=1.1.0
Requires-Dist: lancedb>=0.5.4
Requires-Dist: langchain>=0.3.1
Requires-Dist: litellm>=1.44.22
Requires-Dist: openai>=1.13.3
Requires-Dist: openpyxl>=3.1.5
Requires-Dist: opentelemetry-api>=1.22.0
Requires-Dist: opentelemetry-exporter-otlp-proto-http>=1.22.0
Requires-Dist: opentelemetry-sdk>=1.22.0
Requires-Dist: pdfplumber>=0.11.4
Requires-Dist: pydantic>=2.6.1
Requires-Dist: pytest>=8.0.0
Requires-Dist: python-dotenv>=1.0.0
Requires-Dist: pytube>=15.0.0
Requires-Dist: pyvis>=0.3.2
Requires-Dist: regex>=2024.9.11
Requires-Dist: requests>=2.31.0
Requires-Dist: selenium>=4.18.1
Requires-Dist: tomli-w>=1.1.0
Requires-Dist: tomli>=2.0.2
Requires-Dist: uv>=0.4.25
Provides-Extra: agentops
Requires-Dist: agentops>=0.3.0; extra == 'agentops'
Provides-Extra: fastembed
Requires-Dist: fastembed>=0.4.1; extra == 'fastembed'
Provides-Extra: mem0
Requires-Dist: mem0ai>=0.1.29; extra == 'mem0'
Provides-Extra: openpyxl
Requires-Dist: openpyxl>=3.1.5; extra == 'openpyxl'
Provides-Extra: pandas
Requires-Dist: pandas>=2.2.3; extra == 'pandas'
Provides-Extra: pdfplumber
Requires-Dist: pdfplumber>=0.11.4; extra == 'pdfplumber'
